pydrive4/__init__.py
pydrive4/auth.py
pydrive4/drive.py
pydrive4/exceptions.py
pydrive4/py.typed
pydrive4/operations/__init__.py
pydrive4/operations/base.py
pydrive4/operations/bulk.py
pydrive4/operations/files.py
pydrive4/operations/folders.py
pydrive4/operations/sharing.py
pydrive4-0.0.3.dist-info/METADATA
pydrive4-0.0.3.dist-info/WHEEL
pydrive4-0.0.3.dist-info/licenses/LICENSE
pydrive4-0.0.3.dist-info/RECORD
