Metadata-Version: 2.4
Name: pydrive4
Version: 0.0.3
Summary: PyDrive4: Modern Python library for Google Drive API v3 - Easy file upload, download, folder management with OAuth2, service account & ADC authentication. Simplified wrapper for google-api-python-client
Project-URL: Homepage, https://github.com/SSujitX/pydrive4
Project-URL: Repository, https://github.com/SSujitX/pydrive4
Project-URL: Documentation, https://github.com/SSujitX/pydrive4#readme
Project-URL: Issues, https://github.com/SSujitX/pydrive4/issues
License: MIT
License-File: LICENSE
Keywords: application-default-credentials,cloud-storage,drive-api-simplified,drive-api-v3,drive-api-wrapper,drive-file-download,drive-file-upload,drive-folder-management,file-management,google-api,google-api-python-client,google-drive,google-drive-api-v3,google-drive-automation,google-drive-backup,google-drive-library,google-drive-python,google-drive-sdk,google-drive-search,google-drive-sync,oauth2-google-drive,pydrive,pydrive2,pydrive4,python-cloud-storage,python-drive-client,python-google-driv
Classifier: Development Status :: 4 - Beta
Classifier: Intended Audience :: Developers
Classifier: License :: OSI Approved :: MIT License
Classifier: Programming Language :: Python :: 3
Classifier: Programming Language :: Python :: 3.10
Classifier: Programming Language :: Python :: 3.11
Classifier: Programming Language :: Python :: 3.12
Classifier: Programming Language :: Python :: 3.13
Classifier: Programming Language :: Python :: 3.14
Classifier: Topic :: Internet
Classifier: Topic :: Software Development :: Libraries :: Python Modules
Requires-Python: >=3.10
Requires-Dist: google-api-python-client>=2.100.0
Requires-Dist: google-auth-httplib2>=0.2.0
Requires-Dist: google-auth-oauthlib<=1.2.3,>=1.0.0
Requires-Dist: google-auth<2.42.0,>=2.15.0
